setup.cfg
setup.py
pickthat/__init__.py
pickthat/_version.py
pickthat/api.py
pickthat/image.py
pickthat/mmorph.py
pickthat/pick.py
pickthat/pt.py
pickthat/user.py
pickthat.egg-info/PKG-INFO
pickthat.egg-info/SOURCES.txt
pickthat.egg-info/dependency_links.txt
pickthat.egg-info/not-zip-safe
pickthat.egg-info/requires.txt
pickthat.egg-info/top_level.txt