Metadata-Version: 1.1
Name: pickthat
Version: 0.1.1
Summary: Tools for accessing pickthis.io and analysing results.
Home-page: http://github.com/agile-geoscience/pickthat
Author: Agile Geoscience
Author-email: hello@agilegeoscience.com
License: Apache 2
Platform: UNKNOWN
Classifier: Development Status :: 4 - Beta
Classifier: Intended Audience :: Science/Research
Classifier: Natural Language :: English
Classifier: License :: OSI Approved :: Apache Software License
Classifier: Operating System :: OS Independent
Classifier: Programming Language :: Python
Classifier: Programming Language :: Python :: 2.7
Classifier: Programming Language :: Python :: 3.3
Classifier: Programming Language :: Python :: 3.4
